lzpy/__init__.py
lzpy/dset.py
lzpy/groupmap.py
lzpy/keymap.py
lzpy/mpl_interaction.py
lzpy/node.py
lzpy/row.py
lzpy/rows.py
lzpy/table.py
lzpy/utility.py
lzpy-0.0.32.dist-info/LICENSE
lzpy-0.0.32.dist-info/METADATA
lzpy-0.0.32.dist-info/WHEEL
lzpy-0.0.32.dist-info/top_level.txt
lzpy-0.0.32.dist-info/RECORD
